trainlytics/__init__.py
trainlytics/clean.py
trainlytics/features.py
trainlytics/ingest.py
trainlytics/model.py
trainlytics/recommender.py
trainlytics-0.1.0.dist-info/METADATA
trainlytics-0.1.0.dist-info/WHEEL
trainlytics-0.1.0.dist-info/top_level.txt
trainlytics-0.1.0.dist-info/RECORD
