Metadata-Version: 2.4
Name: trainlytics
Version: 0.1.0
Summary: Open-source Python package for workout analysis and recommendations.
Author-email: Rodrigo Costa <rodrigocosta8638@gmail.com>
License-Expression: MIT
Project-URL: Homepage, https://github.com/Raoc1987/trainlytics
Project-URL: Documentation, https://raoc1987.github.io/trainlytics
Requires-Python: >=3.8
Requires-Dist: pandas
Requires-Dist: numpy
Requires-Dist: scikit-learn
Requires-Dist: matplotlib
Requires-Dist: plotly
Requires-Dist: pytest
Requires-Dist: flake8
Requires-Dist: black
Requires-Dist: streamlit
